{
    "type": "minecraft:crafting_shaped",
    "pattern": [
        "#S#",
        "#N#",
        " / "
    ],
    "key": {
        "#": {
            "item": "minecraft:iron_nugget"
        },
        "S": {
            "item": "minecraft:note_block"
        },
        "N": {
            "item": "minecraft:ender_pearl",
            "data": "{display:{Name:'{\"text\":\"Ender Link\",\"bold\":false,\"italic\":false,\"underlined\":false,\"strikethrough\":false,\"obfuscated\":false}'},Enchantments:[{}],ender_link:1}"
        },
        "/": {
            "item": "minecraft:stick"
        }
    },
    "result": {
        "item": "minecraft:tripwire_hook",
        "count": 1,
        "data": "{display:{Name:'{\"text\":\"Ender Trigger\",\"bold\":false,\"italic\":false,\"underlined\":false,\"strikethrough\":false,\"obfuscated\":false}'},ender_trigger:1}"
    },
    "group": "ender"
}